mhi/cosim/__init__.py
mhi/cosim/__main__.py
mhi/cosim/_cosim.cp310-win_amd64.pyd
mhi/cosim/mhi-cosim.chm
mhi_cosim-1.2.1.dist-info/LICENSE
mhi_cosim-1.2.1.dist-info/METADATA
mhi_cosim-1.2.1.dist-info/WHEEL
mhi_cosim-1.2.1.dist-info/top_level.txt
mhi_cosim-1.2.1.dist-info/RECORD
