Metadata-Version: 2.1
Name: mhi-cosim
Version: 1.2.1
Summary: MHI Cosimulation Module
Home-page: https://www.pscad.com/webhelp-v5-al/index.html
Author: Manitoba Hydro International Ltd.
Author-email: pscad@mhi.ca
License: BSD License
Classifier: Development Status :: 5 - Production/Stable
Classifier: Intended Audience :: Science/Research
Classifier: Programming Language :: Python :: 3
Classifier: Programming Language :: Python :: 3.6
Classifier: Programming Language :: Python :: 3.7
Classifier: Programming Language :: Python :: 3.8
Classifier: Programming Language :: Python :: 3.9
Classifier: Programming Language :: Python :: 3.10
Classifier: Programming Language :: Python :: 3.11
Classifier: Programming Language :: Python :: 3.12
Classifier: Programming Language :: Python :: 3.13
Classifier: Operating System :: Microsoft :: Windows
Requires: wheel
Requires-Python: >=3.6
License-File: LICENSE
